[
  {
    "localPath": "/media/animations/floating-books.svg",
    "title": "Floating Books Animation (Original)",
    "creator": "REVOLQNEXUS",
    "source": "Original work",
    "provider": "In-house",
    "license": "Proprietary",
    "licenseUrl": "N/A",
    "attributionRequired": false,
    "commercialUseChecked": true,
    "checkedAt": "2026-07-10",
    "notes": "Original SVG animation created for this project"
  },
  {
    "localPath": "/media/animations/exam-paper-shuffle.svg",
    "title": "Exam Paper Shuffle Animation (Original)",
    "creator": "REVOLQNEXUS",
    "source": "Original work",
    "provider": "In-house",
    "license": "Proprietary",
    "licenseUrl": "N/A",
    "attributionRequired": false,
    "commercialUseChecked": true,
    "checkedAt": "2026-07-10",
    "notes": "Original SVG animation created for this project"
  },
  {
    "localPath": "/media/animations/coffee-steam.svg",
    "title": "Coffee Steam Animation (Original)",
    "creator": "REVOLQNEXUS",
    "source": "Original work",
    "provider": "In-house",
    "license": "Proprietary",
    "licenseUrl": "N/A",
    "attributionRequired": false,
    "commercialUseChecked": true,
    "checkedAt": "2026-07-10",
    "notes": "Original SVG animation created for this project"
  },
  {
    "localPath": "/media/animations/study-panic.svg",
    "title": "Study Panic Character (Original)",
    "creator": "REVOLQNEXUS",
    "source": "Original work",
    "provider": "In-house",
    "license": "Proprietary",
    "licenseUrl": "N/A",
    "attributionRequired": false,
    "commercialUseChecked": true,
    "checkedAt": "2026-07-10",
    "notes": "Original SVG character animation for landing funnel scene 1 — stressed student energy"
  },
  {
    "localPath": "/media/animations/suspicious-squint.svg",
    "title": "Suspicious Squint Character (Original)",
    "creator": "REVOLQNEXUS",
    "source": "Original work",
    "provider": "In-house",
    "license": "Proprietary",
    "licenseUrl": "N/A",
    "attributionRequired": false,
    "commercialUseChecked": true,
    "checkedAt": "2026-07-10",
    "notes": "Original SVG character animation for landing funnel scene 2 — suspicious/skeptical energy"
  },
  {
    "localPath": "/media/animations/celebration-wave.svg",
    "title": "Celebration Wave Character (Original)",
    "creator": "REVOLQNEXUS",
    "source": "Original work",
    "provider": "In-house",
    "license": "Proprietary",
    "licenseUrl": "N/A",
    "attributionRequired": false,
    "commercialUseChecked": true,
    "checkedAt": "2026-07-10",
    "notes": "Original SVG character animation for landing funnel scene 3 — welcoming/celebration energy"
  },
  {
    "localPath": "/media/animations/come-here.svg",
    "title": "Come Here Beckoning Character (Original)",
    "creator": "REVOLQNEXUS",
    "source": "Original work",
    "provider": "In-house",
    "license": "Proprietary",
    "licenseUrl": "N/A",
    "attributionRequired": false,
    "commercialUseChecked": true,
    "checkedAt": "2026-07-10",
    "notes": "Original SVG character animation for landing funnel scene 4 — beckoning/pointing energy"
  },
  {
    "localPath": "/media/study-culture/scene1-study-stress.gif",
    "title": "Scene 1 — Study Stress GIF",
    "creator": "Purchased",
    "source": "Purchased by REVOLQNEXUS",
    "provider": "Purchased",
    "license": "Purchased / Commercial Use Cleared",
    "licenseUrl": "N/A",
    "attributionRequired": false,
    "commercialUseChecked": true,
    "checkedAt": "2026-07-10",
    "notes": "Landing funnel scene 1 — tired/stressed studying energy. Purchased by project owner."
  },
  {
    "localPath": "/media/study-culture/scene2-suspicious.gif",
    "title": "Scene 2 — Suspicious Reaction GIF",
    "creator": "Purchased",
    "source": "Purchased by REVOLQNEXUS",
    "provider": "Purchased",
    "license": "Purchased / Commercial Use Cleared",
    "licenseUrl": "N/A",
    "attributionRequired": false,
    "commercialUseChecked": true,
    "checkedAt": "2026-07-10",
    "notes": "Landing funnel scene 2 — suspicious/really? reaction energy. Purchased by project owner."
  },
  {
    "localPath": "/media/study-culture/scene3-celebration.gif",
    "title": "Scene 3 — Celebration / Welcome GIF",
    "creator": "Purchased",
    "source": "Purchased by REVOLQNEXUS",
    "provider": "Purchased",
    "license": "Purchased / Commercial Use Cleared",
    "licenseUrl": "N/A",
    "attributionRequired": false,
    "commercialUseChecked": true,
    "checkedAt": "2026-07-10",
    "notes": "Landing funnel scene 3 — welcoming/celebration energy. Purchased by project owner."
  },
  {
    "localPath": "/media/study-culture/scene4-come-here.gif",
    "title": "Scene 4 — Come Here Beckoning GIF",
    "creator": "Purchased",
    "source": "Purchased by REVOLQNEXUS",
    "provider": "Purchased",
    "license": "Purchased / Commercial Use Cleared",
    "licenseUrl": "N/A",
    "attributionRequired": false,
    "commercialUseChecked": true,
    "checkedAt": "2026-07-10",
    "notes": "Landing funnel scene 4 — beckoning/come here energy. Purchased by project owner."
  }
]
